syncstate_mqtt/__init__.py
syncstate_mqtt/_version.py
syncstate_mqtt-1.0.2.dist-info/LICENSE
syncstate_mqtt-1.0.2.dist-info/METADATA
syncstate_mqtt-1.0.2.dist-info/WHEEL
syncstate_mqtt-1.0.2.dist-info/top_level.txt
syncstate_mqtt-1.0.2.dist-info/RECORD
