Metadata-Version: 2.2
Name: syncstate_mqtt
Version: 1.0.2
Summary: Python dictionary state sync keeper with mqtt, read-only
Author: Goldenbeasty
Project-URL: Homepage, https://github.com/goldenbeasty/syncstate_mqtt
Project-URL: Issues, https://github.com/goldenbeasty/syncstate_mqtt/issues
Classifier: Programming Language :: Python :: 3
Classifier: Operating System :: OS Independent
Classifier: License :: OSI Approved :: GNU Affero General Public License v3
Requires-Python: >=3.8
License-File: LICENSE
Requires-Dist: paho-mqtt
